phish_ai_api/__init__.py
phish_ai_api-1.7.dist-info/METADATA
phish_ai_api-1.7.dist-info/RECORD
phish_ai_api-1.7.dist-info/WHEEL
phish_ai_api-1.7.dist-info/top_level.txt
