Metadata-Version: 2.1
Name: phish-ai-api
Version: 1.7
Summary: Phish.AI API wrapper
Home-page: https://github.com/phishai/phish-ai-api
Author: Yevgeny Pats
Author-email: yp@phish.ai
License: UNKNOWN
Platform: UNKNOWN
Classifier: Intended Audience :: Developers
Classifier: Natural Language :: English
Classifier: License :: OSI Approved :: MIT License
Classifier: Programming Language :: Python :: 2.7
Classifier: Programming Language :: Python :: 3.5
